{"ayat_mp3":"https://everyayah.com/data/Alafasy_128kbps/001007.mp3","arabic":"صِرَٰطَ ٱلَّذِينَ أَنۡعَمۡتَ عَلَيۡهِمۡ غَيۡرِ ٱلۡمَغۡضُوبِ عَلَيۡهِمۡ وَلَا ٱلضَّآلِّينَ","bengali":"সে সমস্ত লোকের পথ, যাদেরকে তুমি নেয়ামত দান করেছ। তাদের পথ নয়, যাদের প্রতি তোমার গজব নাযিল হয়েছে এবং যারা পথভ্রষ্ট হয়েছে।","english":"The Way of those on whom You have bestowed Your Grace, not (the way) of those who earned Your Anger, nor of those who went astray","wbw":[{"bengali":"(সেই) পথে","english":"(The) path","en_t":"sirata","arabic":"صِرَٰطَ","ar_mp3":"https://words.audios.quranwbw.com/1/001_007_001.mp3"},{"bengali":"যাদেরকে","english":"(of) those","en_t":"alladhina","arabic":"ٱلَّذِينَ","ar_mp3":"https://words.audios.quranwbw.com/1/001_007_002.mp3"},{"bengali":"আপনি অনুগ্রহ দান করেছেন","english":"You have bestowed (Your) Favors","en_t":"an'amta","arabic":"أَنۡعَمۡتَ","ar_mp3":"https://words.audios.quranwbw.com/1/001_007_003.mp3"},{"bengali":"তাদের উপর","english":"on them","en_t":"alayhim","arabic":"عَلَيۡهِمۡ","ar_mp3":"https://words.audios.quranwbw.com/1/001_007_004.mp3"},{"bengali":"নয় (পথ)","english":"not (of)","en_t":"ghayri","arabic":"غَيۡرِ","ar_mp3":"https://words.audios.quranwbw.com/1/001_007_005.mp3"},{"bengali":"অভিশপ্তদের","english":"those who earned (Your) wrath","en_t":"al-maghdubi","arabic":"ٱلۡمَغۡضُوبِ","ar_mp3":"https://words.audios.quranwbw.com/1/001_007_006.mp3"},{"bengali":"যাদের উপর (গজব পরেছে)","english":"on themselves","en_t":"alayhim","arabic":"عَلَيۡهِمۡ","ar_mp3":"https://words.audios.quranwbw.com/1/001_007_007.mp3"},{"bengali":"এবং না","english":"and not","en_t":"wala","arabic":"وَلَا","ar_mp3":"https://words.audios.quranwbw.com/1/001_007_008.mp3"},{"bengali":"পথভ্রষ্টদের","english":"(of) those who go astray","en_t":"al-dalina","arabic":"ٱلضَّآلِّينَ","ar_mp3":"https://words.audios.quranwbw.com/1/001_007_009.mp3"}]}