{"ayat_mp3":"https://everyayah.com/data/Alafasy_128kbps/002034.mp3","arabic":"وَإِذۡ قُلۡنَا لِلۡمَلَٰٓئِكَةِ ٱسۡجُدُواْ لِأٓدَمَ فَسَجَدُوٓاْ إِلَّآ إِبۡلِيسَ أَبَىٰ وَٱسۡتَكۡبَرَ وَكَانَ مِنَ ٱلۡكَٰفِرِينَ","bengali":"এবং যখন আমি হযরত আদম (আঃ)-কে সেজদা করার জন্য ফেরেশতাগণকে নির্দেশ দিলাম, তখনই ইবলীস ব্যতীত সবাই সিজদা করলো। সে (নির্দেশ) পালন করতে অস্বীকার করল এবং অহংকার প্রদর্শন করল। ফলে সে কাফেরদের অন্তর্ভূক্ত হয়ে গেল।","english":"And (remember) when We said to the angels: \"Prostrate yourselves before Adam.\". And they prostrated except Iblis (Satan), he refused and was proud and was one of the disbelievers (disobedient to Allah)","wbw":[{"bengali":"এবং যখন","english":"And when","en_t":"wa-idh","arabic":"وَإِذۡ","ar_mp3":"https://words.audios.quranwbw.com/2/002_034_001.mp3"},{"bengali":"আমরা বলেছিলাম","english":"We said","en_t":"qul'na","arabic":"قُلۡنَا","ar_mp3":"https://words.audios.quranwbw.com/2/002_034_002.mp3"},{"bengali":"ফেরেশতাদেরকে","english":"to the angels","en_t":"lil'malaikati","arabic":"لِلۡمَلَٰٓئِكَةِ","ar_mp3":"https://words.audios.quranwbw.com/2/002_034_003.mp3"},{"bengali":"''তোমরা সিজদা করো","english":"Prostrate","en_t":"us'judu","arabic":"ٱسۡجُدُواْ","ar_mp3":"https://words.audios.quranwbw.com/2/002_034_004.mp3"},{"bengali":"আদমকে''","english":"to Adam","en_t":"liadama","arabic":"لِأٓدَمَ","ar_mp3":"https://words.audios.quranwbw.com/2/002_034_005.mp3"},{"bengali":"তখন তারা সিজদা করল","english":"[so] they prostrated","en_t":"fasajadu","arabic":"فَسَجَدُوٓاْ","ar_mp3":"https://words.audios.quranwbw.com/2/002_034_006.mp3"},{"bengali":"ব্যতীত","english":"except","en_t":"illa","arabic":"إِلَّآ","ar_mp3":"https://words.audios.quranwbw.com/2/002_034_007.mp3"},{"bengali":"ইবলিস","english":"Iblis","en_t":"ib'lisa","arabic":"إِبۡلِيسَ","ar_mp3":"https://words.audios.quranwbw.com/2/002_034_008.mp3"},{"bengali":"সে অমান্য করল","english":"He refused","en_t":"aba","arabic":"أَبَىٰ","ar_mp3":"https://words.audios.quranwbw.com/2/002_034_009.mp3"},{"bengali":"ও অহংকার করল,","english":"and was arrogant","en_t":"wa-is'takbara","arabic":"وَٱسۡتَكۡبَرَ","ar_mp3":"https://words.audios.quranwbw.com/2/002_034_010.mp3"},{"bengali":"এবং সে হল","english":"and became","en_t":"wakana","arabic":"وَكَانَ","ar_mp3":"https://words.audios.quranwbw.com/2/002_034_011.mp3"},{"bengali":"অন্তর্ভুক্ত","english":"of","en_t":"mina","arabic":"مِنَ","ar_mp3":"https://words.audios.quranwbw.com/2/002_034_012.mp3"},{"bengali":"কাফিরদের","english":"the disbelievers","en_t":"al-kafirina","arabic":"ٱلۡكَٰفِرِينَ","ar_mp3":"https://words.audios.quranwbw.com/2/002_034_013.mp3"}]}