{"ayat_mp3":"https://everyayah.com/data/Alafasy_128kbps/002131.mp3","arabic":"إِذۡ قَالَ لَهُۥ رَبُّهُۥٓ أَسۡلِمۡۖ قَالَ أَسۡلَمۡتُ لِرَبِّ ٱلۡعَٰلَمِينَ","bengali":"স্মরণ কর, যখন তাকে তার পালনকর্তা বললেনঃ অনুগত হও। সে বললঃ আমি বিশ্বপালকের অনুগত হলাম।","english":"When his Lord said to him, \"Submit (i.e. be a Muslim)!\" He said, \"I have submitted myself (as a Muslim) to the Lord of the 'Alamin (mankind, jinns and all that exists)","wbw":[{"bengali":"(সে ছিল এমন যে) যখন","english":"When","en_t":"idh","arabic":"إِذۡ","ar_mp3":"https://words.audios.quranwbw.com/2/002_131_001.mp3"},{"bengali":"বলেছিলেন","english":"said","en_t":"qala","arabic":"قَالَ","ar_mp3":"https://words.audios.quranwbw.com/2/002_131_002.mp3"},{"bengali":"তার","english":"to him","en_t":"lahu","arabic":"لَهُۥ","ar_mp3":"https://words.audios.quranwbw.com/2/002_131_003.mp3"},{"bengali":"তার রব","english":"his Lord","en_t":"rabbuhu","arabic":"رَبُّهُۥٓ","ar_mp3":"https://words.audios.quranwbw.com/2/002_131_004.mp3"},{"bengali":"''তুমি আত্মসমর্পণ করো''","english":"Submit (yourself)","en_t":"aslim","arabic":"أَسۡلِمۡۖ","ar_mp3":"https://words.audios.quranwbw.com/2/002_131_005.mp3"},{"bengali":"সে বলেছিল","english":"he said","en_t":"qala","arabic":"قَالَ","ar_mp3":"https://words.audios.quranwbw.com/2/002_131_006.mp3"},{"bengali":"''আমি আত্মসমর্পণ করলাম","english":"I (have) submitted (myself)","en_t":"aslamtu","arabic":"أَسۡلَمۡتُ","ar_mp3":"https://words.audios.quranwbw.com/2/002_131_007.mp3"},{"bengali":"রবের কাছে","english":"to (the) Lord","en_t":"lirabbi","arabic":"لِرَبِّ","ar_mp3":"https://words.audios.quranwbw.com/2/002_131_008.mp3"},{"bengali":"জগতের''","english":"(of) the worlds","en_t":"al-'alamina","arabic":"ٱلۡعَٰلَمِينَ","ar_mp3":"https://words.audios.quranwbw.com/2/002_131_009.mp3"}]}