{"ayat_mp3":"https://everyayah.com/data/Alafasy_128kbps/002198.mp3","arabic":"لَيۡسَ عَلَيۡكُمۡ جُنَاحٌ أَن تَبۡتَغُواْ فَضۡلٗا مِّن رَّبِّكُمۡۚ فَإِذَآ أَفَضۡتُم مِّنۡ عَرَفَٰتٖ فَٱذۡكُرُواْ ٱللَّهَ عِندَ ٱلۡمَشۡعَرِ ٱلۡحَرَامِۖ وَٱذۡكُرُوهُ كَمَا هَدَىٰكُمۡ وَإِن كُنتُم مِّن قَبۡلِهِۦ لَمِنَ ٱلضَّآلِّينَ","bengali":"তোমাদের উপর তোমাদের পালনকর্তার অনুগ্রহ অন্বেষন করায় কোন পাপ নেই। অতঃপর যখন তওয়াফের জন্য ফিরে আসবে আরাফাত থেকে, তখন মাশ‘ আরে-হারামের নিকটে আল্লাহকে স্মরণ কর। আর তাঁকে স্মরণ কর তেমনি করে, যেমন তোমাদিগকে হেদায়েত করা হয়েছে। আর নিশ্চয়ই ইতিপূর্বে তোমরা ছিলে অজ্ঞ।","english":"There is no sin on you if you seek the Bounty of your Lord (during pilgrimage by trading, etc.). Then when you leave 'Arafat, remember Allah (by glorifying His Praises, i.e. prayers and invocations, etc.) at the Mash'ar-il-Haram. And remember Him (by invoking Allah for all good, etc.) as He has guided you, and verily, you were, before, of those who were astray","wbw":[{"bengali":"নেই","english":"Not is","en_t":"laysa","arabic":"لَيۡسَ","ar_mp3":"https://words.audios.quranwbw.com/2/002_198_001.mp3"},{"bengali":"তোমাদের উপর","english":"on you","en_t":"alaykum","arabic":"عَلَيۡكُمۡ","ar_mp3":"https://words.audios.quranwbw.com/2/002_198_002.mp3"},{"bengali":"কোন পাপ","english":"any sin","en_t":"junahun","arabic":"جُنَاحٌ","ar_mp3":"https://words.audios.quranwbw.com/2/002_198_003.mp3"},{"bengali":"যে","english":"that","en_t":"an","arabic":"أَن","ar_mp3":"https://words.audios.quranwbw.com/2/002_198_004.mp3"},{"bengali":"তোমরা সন্ধান করবে","english":"you seek","en_t":"tabtaghu","arabic":"تَبۡتَغُواْ","ar_mp3":"https://words.audios.quranwbw.com/2/002_198_005.mp3"},{"bengali":"অনুগ্রহ","english":"bounty","en_t":"fadlan","arabic":"فَضۡلٗا","ar_mp3":"https://words.audios.quranwbw.com/2/002_198_006.mp3"},{"bengali":"কাছ থেকে","english":"from","en_t":"min","arabic":"مِّن","ar_mp3":"https://words.audios.quranwbw.com/2/002_198_007.mp3"},{"bengali":"তোমাদের রবের","english":"your Lord","en_t":"rabbikum","arabic":"رَّبِّكُمۡۚ","ar_mp3":"https://words.audios.quranwbw.com/2/002_198_008.mp3"},{"bengali":"অতঃপর যখন","english":"And when","en_t":"fa-idha","arabic":"فَإِذَآ","ar_mp3":"https://words.audios.quranwbw.com/2/002_198_009.mp3"},{"bengali":"তোমরা প্রত্যাবর্তন কর","english":"you depart","en_t":"afadtum","arabic":"أَفَضۡتُم","ar_mp3":"https://words.audios.quranwbw.com/2/002_198_010.mp3"},{"bengali":"থেকে","english":"from","en_t":"min","arabic":"مِّنۡ","ar_mp3":"https://words.audios.quranwbw.com/2/002_198_011.mp3"},{"bengali":"আরাফাত","english":"(Mount) Arafat","en_t":"arafatin","arabic":"عَرَفَٰتٖ","ar_mp3":"https://words.audios.quranwbw.com/2/002_198_012.mp3"},{"bengali":"তোমরা স্মরণ করো","english":"then remember","en_t":"fa-udh'kuru","arabic":"فَٱذۡكُرُواْ","ar_mp3":"https://words.audios.quranwbw.com/2/002_198_013.mp3"},{"bengali":"আল্লাহকে","english":"Allah","en_t":"al-laha","arabic":"ٱللَّهَ","ar_mp3":"https://words.audios.quranwbw.com/2/002_198_014.mp3"},{"bengali":"কাছে","english":"near","en_t":"inda","arabic":"عِندَ","ar_mp3":"https://words.audios.quranwbw.com/2/002_198_015.mp3"},{"bengali":"মাশআরিল","english":"the Monument","en_t":"al-mash'ari","arabic":"ٱلۡمَشۡعَرِ","ar_mp3":"https://words.audios.quranwbw.com/2/002_198_016.mp3"},{"bengali":"হারামের (মুজাদালেফায়)","english":"[the] Sacred","en_t":"al-harami","arabic":"ٱلۡحَرَامِۖ","ar_mp3":"https://words.audios.quranwbw.com/2/002_198_017.mp3"},{"bengali":"এবং তাকে স্মরণ করো","english":"And remember Him","en_t":"wa-udh'kuruhu","arabic":"وَٱذۡكُرُوهُ","ar_mp3":"https://words.audios.quranwbw.com/2/002_198_018.mp3"},{"bengali":"যেমন","english":"as","en_t":"kama","arabic":"كَمَا","ar_mp3":"https://words.audios.quranwbw.com/2/002_198_019.mp3"},{"bengali":"তোমাদের নির্দেশ দিয়েছেন তিনি","english":"He (has) guided you","en_t":"hadakum","arabic":"هَدَىٰكُمۡ","ar_mp3":"https://words.audios.quranwbw.com/2/002_198_020.mp3"},{"bengali":"এবং যদিও","english":"[and] though","en_t":"wa-in","arabic":"وَإِن","ar_mp3":"https://words.audios.quranwbw.com/2/002_198_021.mp3"},{"bengali":"তোমরা ছিলে","english":"you were","en_t":"kuntum","arabic":"كُنتُم","ar_mp3":"https://words.audios.quranwbw.com/2/002_198_022.mp3"},{"bengali":"থেকে","english":"[from]","en_t":"min","arabic":"مِّن","ar_mp3":"https://words.audios.quranwbw.com/2/002_198_023.mp3"},{"bengali":"এর পূর্বেই","english":"before [it]","en_t":"qablihi","arabic":"قَبۡلِهِۦ","ar_mp3":"https://words.audios.quranwbw.com/2/002_198_024.mp3"},{"bengali":"অবশ্যই অন্তর্ভুক্ত","english":"surely among","en_t":"lamina","arabic":"لَمِنَ","ar_mp3":"https://words.audios.quranwbw.com/2/002_198_025.mp3"},{"bengali":"পথভ্রষ্টদের","english":"those who went astray","en_t":"al-dalina","arabic":"ٱلضَّآلِّينَ","ar_mp3":"https://words.audios.quranwbw.com/2/002_198_026.mp3"}]}